Subplot2Grid/Subplot2Grid.py
Subplot2Grid/__init__.py
Subplot2Grid/__main__.py
Subplot2Grid/s2g.ico
Subplot2Grid-0.0.3.dist-info/METADATA
Subplot2Grid-0.0.3.dist-info/WHEEL
Subplot2Grid-0.0.3.dist-info/top_level.txt
Subplot2Grid-0.0.3.dist-info/RECORD
