Metadata-Version: 2.1
Name: Subplot2Grid
Version: 0.0.3
Summary: Tool to manually draw subplots for Subplot2Grid.
Home-page: https://github.com/ludvikalkhoury/Subplot2Grid.git
Author: Ludvik Alkhoury
Author-email: Ludvik.Alkhoury@gmail.com
Requires-Dist: pyperclip ==1.9.0
Requires-Dist: Pillow >=9.4.0
